[{"type":"Usage","duration":30,"date":"2022-06-06","endTime":"2022-06-05T14:30:00Z","quality":"billable","kwh":0.025,"nemTime":"2022-06-06T00:30:00+10:00","perKwh":15.75734,"channelType":"general","channelIdentifier":"E1","cost":0.3939,"renewables":36.516999999999996,"spotPerKwh":2.12245,"startTime":"2022-06-05T14:00:01Z","spikeStatus":"none","descriptor":"veryLow"},{"type":"Usage","duration":30,"date":"2022-06-06","endTime":"2022-06-05T15:00:00Z","quality":"billable","kwh":0.031,"nemTime":"2022-06-06T01:00:00+10:00","perKwh":15.65659,"channelType":"general","channelIdentifier":"E1","cost":0.4854,"renewables":38.332,"spotPerKwh":2.02639,"startTime":"2022-06-05T14:30:01Z","spikeStatus":"none","descriptor":"veryLow"},{"type":"Usage","duration":30,"date":"2022-06-06","endTime":"2022-06-05T15:30:00Z","quality":"billable","kwh":0.037,"nemTime":"2022-06-06T01:30:00+10:00","perKwh":22.85096,"channelType":"general","channelIdentifier":"E1","cost":0.8455,"renewables":39.734,"spotPerKwh":8.8859,"startTime":"2022-06-05T15:00:01Z","spikeStatus":"none","descriptor":"low"},{"type":"Usage","duration":30,"date":"2022-06-06","endTime":"2022-06-05T16:00:00Z","quality":"billable","kwh":0.019,"nemTime":"2022-06-06T02:00:00+10:00","perKwh":15.44584,"channelType":"general","channelIdentifier":"E1","cost":0.2935,"renewables":42.553999999999995,"spotPerKwh":1.82545,"startTime":"2022-06-05T15:30:01Z","spikeStatus":"none","descriptor":"veryLow"},{"type":"Usage","duration":30,"date":"2022-06-06","endTime":"2022-06-05T16:30:00Z","quality":"billable","kwh":0.025,"nemTime":"2022-06-06T02:30:00+10:00","perKwh":16.9455,"channelType":"general","channelIdentifier":"E1","cost":0.4236,"renewables":43.492,"spotPerKwh":3.25531,"startTime":"2022-06-05T16:00:01Z","spikeStatus":"none","descriptor":"veryLow"},{"type":"Usage","duration":30,"date":"2022-06-06","endTime":"2022-06-05T17:00:00Z","quality":"billable","kwh":0.037,"nemTime":"2022-06-06T03:00:00+10:00","perKwh":15.74292,"channelType":"general","channelIdentifier":"E1","cost":0.5825,"renewables":45.635999999999996,"spotPerKwh":2.1087,"startTime":"2022-06-05T16:30:01Z","spikeStatus":"none","descriptor":"veryLow"},{"type":"Usage","duration":30,"date":"2022-06-06","endTime":"2022-06-05T17:30:00Z","quality":"billable","kwh":0.019,"nemTime":"2022-06-06T03:30:00+10:00","perKwh":15.61931,"channelType":"general","channelIdentifier":"E1","cost":0.2968,"renewables":47.39,"spotPerKwh":1.99084,"startTime":"2022-06-05T17:00:01Z","spikeStatus":"none","descriptor":"veryLow"},{"type":"Usage","duration":30,"date":"2022-06-06","endTime":"2022-06-05T18:00:00Z","quality":"billable","kwh":0.019,"nemTime":"2022-06-06T04:00:00+10:00","perKwh":16.38701,"channelType":"general","channelIdentifier":"E1","cost":0.3114,"renewables":46.761,"spotPerKwh":2.72281,"startTime":"2022-06-05T17:30:01Z","spikeStatus":"none","descriptor":"veryLow"},{"type":"Usage","duration":30,"date":"2022-06-06","endTime":"2022-06-05T18:30:00Z","quality":"billable","kwh":0.044,"nemTime":"2022-06-06T04:30:00+10:00","perKwh":20.08975,"channelType":"general","channelIdentifier":"E1","cost":0.8839,"renewables":42.07,"spotPerKwh":6.25321,"startTime":"2022-06-05T18:00:01Z","spikeStatus":"none","descriptor":"veryLow"},{"type":"Usage","duration":30,"date":"2022-06-06","endTime":"2022-06-05T19:00:00Z","quality":"billable","kwh":0.025,"nemTime":"2022-06-06T05:00:00+10:00","perKwh":14.29164,"channelType":"general","channelIdentifier":"E1","cost":0.3573,"renewables":45.388,"spotPerKwh":0.72497,"startTime":"2022-06-05T18:30:01Z","spikeStatus":"none","descriptor":"veryLow"},{"type":"Usage","duration":30,"date":"2022-06-06","endTime":"2022-06-05T19:30:00Z","quality":"billable","kwh":0.019,"nemTime":"2022-06-06T05:30:00+10:00","perKwh":14.72901,"channelType":"general","channelIdentifier":"E1","cost":0.2799,"renewables":44.777,"spotPerKwh":1.14198,"startTime":"2022-06-05T19:00:01Z","spikeStatus":"none","descriptor":"veryLow"},{"type":"Usage","duration":30,"date":"2022-06-06","endTime":"2022-06-05T20:00:00Z","quality":"billable","kwh":0.031,"nemTime":"2022-06-06T06:00:00+10:00","perKwh":22.04766,"channelType":"general","channelIdentifier":"E1","cost":0.6835,"renewables":37.277,"spotPerKwh":8.11999,"startTime":"2022-06-05T19:30:01Z","spikeStatus":"none","descriptor":"low"},{"type":"Usage","duration":30,"date":"2022-06-06","endTime":"2022-06-05T20:30:00Z","quality":"billable","kwh":0.031,"nemTime":"2022-06-06T06:30:00+10:00","perKwh":36.57282,"channelType":"general","channelIdentifier":"E1","cost":1.1338,"renewables":34.857,"spotPerKwh":21.96909,"startTime":"2022-06-05T20:00:01Z","spikeStatus":"none","descriptor":"neutral"},{"type":"Usage","duration":30,"date":"2022-06-06","endTime":"2022-06-05T21:00:00Z","quality":"billable","kwh":0.019,"nemTime":"2022-06-06T07:00:00+10:00","perKwh":58.70416,"channelType":"general","channelIdentifier":"E1","cost":1.1154,"renewables":31.709,"spotPerKwh":43.07035,"startTime":"2022-06-05T20:30:01Z","spikeStatus":"none","descriptor":"high"},{"type":"Usage","duration":30,"date":"2022-06-06","endTime":"2022-06-05T21:30:00Z","quality":"billable","kwh":0.019,"nemTime":"2022-06-06T07:30:00+10:00","perKwh":60.88764,"channelType":"general","channelIdentifier":"E1","cost":1.1569,"renewables":27.715,"spotPerKwh":45.1522,"startTime":"2022-06-05T21:00:01Z","spikeStatus":"none","descriptor":"high"},{"type":"Usage","duration":30,"date":"2022-06-06","endTime":"2022-06-05T22:00:00Z","quality":"billable","kwh":0.525,"nemTime":"2022-06-06T08:00:00+10:00","perKwh":63.39027,"channelType":"general","channelIdentifier":"E1","cost":33.2799,"renewables":26.255,"spotPerKwh":47.53835,"startTime":"2022-06-05T21:30:01Z","spikeStatus":"none","descriptor":"high"},{"type":"Usage","duration":30,"date":"2022-06-06","endTime":"2022-06-05T22:30:00Z","quality":"billable","kwh":0.194,"nemTime":"2022-06-06T08:30:00+10:00","perKwh":64.71642,"channelType":"general","channelIdentifier":"E1","cost":12.555,"renewables":26.851999999999997,"spotPerKwh":48.80277,"startTime":"2022-06-05T22:00:01Z","spikeStatus":"none","descriptor":"high"},{"type":"Usage","duration":30,"date":"2022-06-06","endTime":"2022-06-05T23:00:00Z","quality":"billable","kwh":0.762,"nemTime":"2022-06-06T09:00:00+10:00","perKwh":58.98096,"channelType":"general","channelIdentifier":"E1","cost":44.9435,"renewables":29.144,"spotPerKwh":43.33426,"startTime":"2022-06-05T22:30:01Z","spikeStatus":"none","descriptor":"high"},{"type":"Usage","duration":30,"date":"2022-06-06","endTime":"2022-06-05T23:30:00Z","quality":"billable","kwh":0.744,"nemTime":"2022-06-06T09:30:00+10:00","perKwh":54.67144,"channelType":"general","channelIdentifier":"E1","cost":40.6756,"renewables":29.187,"spotPerKwh":39.22533,"startTime":"2022-06-05T23:00:01Z","spikeStatus":"none","descriptor":"high"},{"type":"Usage","duration":30,"date":"2022-06-06","endTime":"2022-06-06T00:00:00Z","quality":"billable","kwh":0.669,"nemTime":"2022-06-06T10:00:00+10:00","perKwh":47.09556,"channelType":"general","channelIdentifier":"E1","cost":31.5069,"renewables":31.224,"spotPerKwh":32.00206,"startTime":"2022-06-05T23:30:01Z","spikeStatus":"none","descriptor":"high"},{"type":"Usage","duration":30,"date":"2022-06-06","endTime":"2022-06-06T00:30:00Z","quality":"billable","kwh":0.625,"nemTime":"2022-06-06T10:30:00+10:00","perKwh":45.59777,"channelType":"general","channelIdentifier":"E1","cost":28.4986,"renewables":33.158,"spotPerKwh":30.57398,"startTime":"2022-06-06T00:00:01Z","spikeStatus":"none","descriptor":"high"},{"type":"Usage","duration":30,"date":"2022-06-06","endTime":"2022-06-06T01:00:00Z","quality":"billable","kwh":0.65,"nemTime":"2022-06-06T11:00:00+10:00","perKwh":23.17126,"channelType":"general","channelIdentifier":"E1","cost":15.0613,"renewables":36.6,"spotPerKwh":9.19129,"startTime":"2022-06-06T00:30:01Z","spikeStatus":"none","descriptor":"low"},{"type":"Usage","duration":30,"date":"2022-06-06","endTime":"2022-06-06T01:30:00Z","quality":"billable","kwh":0.637,"nemTime":"2022-06-06T11:30:00+10:00","perKwh":12.54313,"channelType":"general","channelIdentifier":"E1","cost":7.99,"renewables":39.92,"spotPerKwh":-0.94216,"startTime":"2022-06-06T01:00:01Z","spikeStatus":"none","descriptor":"extremelyLow"},{"type":"Usage","duration":30,"date":"2022-06-06","endTime":"2022-06-06T02:00:00Z","quality":"billable","kwh":0.625,"nemTime":"2022-06-06T12:00:00+10:00","perKwh":15.55472,"channelType":"general","channelIdentifier":"E1","cost":9.7217,"renewables":45.011,"spotPerKwh":1.92926,"startTime":"2022-06-06T01:30:01Z","spikeStatus":"none","descriptor":"veryLow"},{"type":"Usage","duration":30,"date":"2022-06-06","endTime":"2022-06-06T02:30:00Z","quality":"billable","kwh":0.087,"nemTime":"2022-06-06T12:30:00+10:00","perKwh":15.38075,"channelType":"general","channelIdentifier":"E1","cost":1.3381,"renewables":45.112,"spotPerKwh":1.76339,"startTime":"2022-06-06T02:00:01Z","spikeStatus":"none","descriptor":"veryLow"},{"type":"Usage","duration":30,"date":"2022-06-06","endTime":"2022-06-06T03:00:00Z","quality":"billable","kwh":0.225,"nemTime":"2022-06-06T13:00:00+10:00","perKwh":15.69194,"channelType":"general","channelIdentifier":"E1","cost":3.5307,"renewables":43.669999999999995,"spotPerKwh":2.06009,"startTime":"2022-06-06T02:30:01Z","spikeStatus":"none","descriptor":"veryLow"},{"type":"Usage","duration":30,"date":"2022-06-06","endTime":"2022-06-06T03:30:00Z","quality":"billable","kwh":0.063,"nemTime":"2022-06-06T13:30:00+10:00","perKwh":18.00255,"channelType":"general","channelIdentifier":"E1","cost":1.1342,"renewables":39.836,"spotPerKwh":4.26316,"startTime":"2022-06-06T03:00:01Z","spikeStatus":"none","descriptor":"veryLow"},{"type":"Usage","duration":30,"date":"2022-06-06","endTime":"2022-06-06T04:00:00Z","quality":"billable","kwh":0.119,"nemTime":"2022-06-06T14:00:00+10:00","perKwh":30.18396,"channelType":"general","channelIdentifier":"E1","cost":3.5919,"renewables":37.552,"spotPerKwh":15.87759,"startTime":"2022-06-06T03:30:01Z","spikeStatus":"none","descriptor":"low"},{"type":"Usage","duration":30,"date":"2022-06-06","endTime":"2022-06-06T04:30:00Z","quality":"billable","kwh":0.044,"nemTime":"2022-06-06T14:30:00+10:00","perKwh":41.31154,"channelType":"general","channelIdentifier":"E1","cost":1.8177,"renewables":32.375,"spotPerKwh":26.48725,"startTime":"2022-06-06T04:00:01Z","spikeStatus":"none","descriptor":"neutral"},{"type":"Usage","duration":30,"date":"2022-06-06","endTime":"2022-06-06T05:00:00Z","quality":"billable","kwh":0.069,"nemTime":"2022-06-06T15:00:00+10:00","perKwh":46.23036,"channelType":"general","channelIdentifier":"E1","cost":3.1899,"renewables":34.547,"spotPerKwh":31.17713,"startTime":"2022-06-06T04:30:01Z","spikeStatus":"none","descriptor":"high"},{"type":"Usage","duration":30,"date":"2022-06-06","endTime":"2022-06-06T05:30:00Z","quality":"billable","kwh":0.044,"nemTime":"2022-06-06T15:30:00+10:00","perKwh":47.52664,"channelType":"general","channelIdentifier":"E1","cost":2.0912,"renewables":33.867999999999995,"spotPerKwh":32.41307,"startTime":"2022-06-06T05:00:01Z","spikeStatus":"none","descriptor":"high"},{"type":"Usage","duration":30,"date":"2022-06-06","endTime":"2022-06-06T06:00:00Z","quality":"billable","kwh":0.056,"nemTime":"2022-06-06T16:00:00+10:00","perKwh":47.07261,"channelType":"general","channelIdentifier":"E1","cost":2.6361,"renewables":30.991000000000003,"spotPerKwh":31.98018,"startTime":"2022-06-06T05:30:01Z","spikeStatus":"none","descriptor":"high"},{"type":"Usage","duration":30,"date":"2022-06-06","endTime":"2022-06-06T06:30:00Z","quality":"billable","kwh":0.056,"nemTime":"2022-06-06T16:30:00+10:00","perKwh":51.73533,"channelType":"general","channelIdentifier":"E1","cost":2.8972,"renewables":28.247,"spotPerKwh":36.42587,"startTime":"2022-06-06T06:00:01Z","spikeStatus":"none","descriptor":"high"},{"type":"Usage","duration":30,"date":"2022-06-06","endTime":"2022-06-06T07:00:00Z","quality":"billable","kwh":0.044,"nemTime":"2022-06-06T17:00:00+10:00","perKwh":60.7411,"channelType":"general","channelIdentifier":"E1","cost":2.6726,"renewables":24.81,"spotPerKwh":45.01248,"startTime":"2022-06-06T06:30:01Z","spikeStatus":"none","descriptor":"high"},{"type":"Usage","duration":30,"date":"2022-06-06","endTime":"2022-06-06T07:30:00Z","quality":"billable","kwh":1.144,"nemTime":"2022-06-06T17:30:00+10:00","perKwh":67.48533,"channelType":"general","channelIdentifier":"E1","cost":77.2032,"renewables":22.607,"spotPerKwh":51.4428,"startTime":"2022-06-06T07:00:01Z","spikeStatus":"none","descriptor":"high"},{"type":"Usage","duration":30,"date":"2022-06-06","endTime":"2022-06-06T08:00:00Z","quality":"billable","kwh":0.812,"nemTime":"2022-06-06T18:00:00+10:00","perKwh":62.36752,"channelType":"general","channelIdentifier":"E1","cost":50.6424,"renewables":20.841,"spotPerKwh":46.5632,"startTime":"2022-06-06T07:30:01Z","spikeStatus":"none","descriptor":"high"},{"type":"Usage","duration":30,"date":"2022-06-06","endTime":"2022-06-06T08:30:00Z","quality":"billable","kwh":0.475,"nemTime":"2022-06-06T18:30:00+10:00","perKwh":62.93828,"channelType":"general","channelIdentifier":"E1","cost":29.8957,"renewables":20.782999999999998,"spotPerKwh":47.10739,"startTime":"2022-06-06T08:00:01Z","spikeStatus":"none","descriptor":"high"},{"type":"Usage","duration":30,"date":"2022-06-06","endTime":"2022-06-06T09:00:00Z","quality":"billable","kwh":0.681,"nemTime":"2022-06-06T19:00:00+10:00","perKwh":62.23691,"channelType":"general","channelIdentifier":"E1","cost":42.3833,"renewables":21.874,"spotPerKwh":46.43867,"startTime":"2022-06-06T08:30:01Z","spikeStatus":"none","descriptor":"high"},{"type":"Usage","duration":30,"date":"2022-06-06","endTime":"2022-06-06T09:30:00Z","quality":"billable","kwh":0.3,"nemTime":"2022-06-06T19:30:00+10:00","perKwh":60.81416,"channelType":"general","channelIdentifier":"E1","cost":18.2442,"renewables":22.149,"spotPerKwh":45.08214,"startTime":"2022-06-06T09:00:01Z","spikeStatus":"none","descriptor":"high"},{"type":"Usage","duration":30,"date":"2022-06-06","endTime":"2022-06-06T10:00:00Z","quality":"billable","kwh":0.119,"nemTime":"2022-06-06T20:00:00+10:00","perKwh":60.13175,"channelType":"general","channelIdentifier":"E1","cost":7.1557,"renewables":24.122,"spotPerKwh":44.43149,"startTime":"2022-06-06T09:30:01Z","spikeStatus":"none","descriptor":"high"},{"type":"Usage","duration":30,"date":"2022-06-06","endTime":"2022-06-06T10:30:00Z","quality":"billable","kwh":0.106,"nemTime":"2022-06-06T20:30:00+10:00","perKwh":57.77962,"channelType":"general","channelIdentifier":"E1","cost":6.1246,"renewables":25.161,"spotPerKwh":42.18884,"startTime":"2022-06-06T10:00:01Z","spikeStatus":"none","descriptor":"high"},{"type":"Usage","duration":30,"date":"2022-06-06","endTime":"2022-06-06T11:00:00Z","quality":"billable","kwh":0.125,"nemTime":"2022-06-06T21:00:00+10:00","perKwh":59.02144,"channelType":"general","channelIdentifier":"E1","cost":7.3777,"renewables":25.918000000000003,"spotPerKwh":43.37286,"startTime":"2022-06-06T10:30:01Z","spikeStatus":"none","descriptor":"high"},{"type":"Usage","duration":30,"date":"2022-06-06","endTime":"2022-06-06T11:30:00Z","quality":"billable","kwh":0.056,"nemTime":"2022-06-06T21:30:00+10:00","perKwh":54.00281,"channelType":"general","channelIdentifier":"E1","cost":3.0242,"renewables":24.999,"spotPerKwh":38.58782,"startTime":"2022-06-06T11:00:01Z","spikeStatus":"none","descriptor":"high"},{"type":"Usage","duration":30,"date":"2022-06-06","endTime":"2022-06-06T12:00:00Z","quality":"billable","kwh":1.137,"nemTime":"2022-06-06T22:00:00+10:00","perKwh":51.80971,"channelType":"general","channelIdentifier":"E1","cost":58.9076,"renewables":26.344,"spotPerKwh":36.49679,"startTime":"2022-06-06T11:30:01Z","spikeStatus":"none","descriptor":"high"},{"type":"Usage","duration":30,"date":"2022-06-06","endTime":"2022-06-06T12:30:00Z","quality":"billable","kwh":0.069,"nemTime":"2022-06-06T22:30:00+10:00","perKwh":48.57556,"channelType":"general","channelIdentifier":"E1","cost":3.3517,"renewables":28.758,"spotPerKwh":33.41317,"startTime":"2022-06-06T12:00:01Z","spikeStatus":"none","descriptor":"high"},{"type":"Usage","duration":30,"date":"2022-06-06","endTime":"2022-06-06T13:00:00Z","quality":"billable","kwh":0.05,"nemTime":"2022-06-06T23:00:00+10:00","perKwh":48.14323,"channelType":"general","channelIdentifier":"E1","cost":2.4072,"renewables":29.193,"spotPerKwh":33.00097,"startTime":"2022-06-06T12:30:01Z","spikeStatus":"none","descriptor":"high"},{"type":"Usage","duration":30,"date":"2022-06-06","endTime":"2022-06-06T13:30:00Z","quality":"billable","kwh":0.037,"nemTime":"2022-06-06T23:30:00+10:00","perKwh":48.01299,"channelType":"general","channelIdentifier":"E1","cost":1.7765,"renewables":29.476999999999997,"spotPerKwh":32.87679,"startTime":"2022-06-06T13:00:01Z","spikeStatus":"none","descriptor":"high"},{"type":"Usage","duration":30,"date":"2022-06-06","endTime":"2022-06-06T14:00:00Z","quality":"billable","kwh":0.056,"nemTime":"2022-06-07T00:00:00+10:00","perKwh":45.77611,"channelType":"general","channelIdentifier":"E1","cost":2.5635,"renewables":31.55,"spotPerKwh":30.74402,"startTime":"2022-06-06T13:30:01Z","spikeStatus":"none","descriptor":"high"}]